hello.py
adsk_ailab_ray-0.0.1.dist-info/METADATA
adsk_ailab_ray-0.0.1.dist-info/WHEEL
adsk_ailab_ray-0.0.1.dist-info/top_level.txt
adsk_ailab_ray-0.0.1.dist-info/RECORD
